sites_microsoft_auth/__init__.py
sites_microsoft_auth/_version.py
sites_microsoft_auth/admin.py
sites_microsoft_auth/apps.py
sites_microsoft_auth/backends.py
sites_microsoft_auth/client.py
sites_microsoft_auth/conf.py
sites_microsoft_auth/context_processors.py
sites_microsoft_auth/models.py
sites_microsoft_auth/old_conf.py
sites_microsoft_auth/signals.py
sites_microsoft_auth/urls.py
sites_microsoft_auth/utils.py
sites_microsoft_auth/views.py
sites_microsoft_auth/migrations/0001_initial.py
sites_microsoft_auth/migrations/0002_auto_20190923_1301.py
sites_microsoft_auth/migrations/0003_auto_20190923_1511.py
sites_microsoft_auth/migrations/0004_auto_20190923_1512.py
sites_microsoft_auth/migrations/0005_auto_20190923_1514.py
sites_microsoft_auth/migrations/0006_auto_20190923_1535.py
sites_microsoft_auth/migrations/0007_auto_20200112_2129.py
sites_microsoft_auth/migrations/0008_auto_20200312_1658.py
sites_microsoft_auth/migrations/0009_auto_20200428_0508.py
sites_microsoft_auth/migrations/0010_auto_20200505_0215.py
sites_microsoft_auth/migrations/0011_auto_20200504_2141.py
sites_microsoft_auth/migrations/__init__.py
sites_microsoft_auth/static/microsoft/css/login.css
sites_microsoft_auth/static/microsoft/js/login.js
sites_microsoft_auth/templates/microsoft/admin_login.html
sites_microsoft_auth/templates/microsoft/auth_callback.html
django_sites_microsoft_auth-1.0.6.dist-info/AUTHORS.rst
django_sites_microsoft_auth-1.0.6.dist-info/LICENSE
django_sites_microsoft_auth-1.0.6.dist-info/METADATA
django_sites_microsoft_auth-1.0.6.dist-info/WHEEL
django_sites_microsoft_auth-1.0.6.dist-info/top_level.txt
django_sites_microsoft_auth-1.0.6.dist-info/RECORD
