Metadata-Version: 2.1
Name: django-sites-microsoft-auth
Version: 1.0.6
Summary: Simple app to enable Microsoft Account, Office 365 Enterprise, Azure AD, and Xbox Live authentication as a Django authentication backend on a per-site basis.
Home-page: https://github.com/gskudder/django_sites_microsoft_auth
Author: Griffin Skudder
Author-email: griffin@skudder.co.nz
License: MIT license
Keywords: django_sites_microsoft_auth
Platform: UNKNOWN
Classifier: Development Status :: 5 - Production/Stable
Classifier: Intended Audience :: Developers
Classifier: License :: OSI Approved :: MIT License
Classifier: Natural Language :: English
Classifier: Programming Language :: Python :: 3
Classifier: Programming Language :: Python :: 3.5
Classifier: Programming Language :: Python :: 3.6
Classifier: Programming Language :: Python :: 3.7
Classifier: Framework :: Django :: 1.11
Classifier: Framework :: Django :: 2.0
Classifier: Framework :: Django :: 2.1
Requires-Dist: Django (>=1.11)
Requires-Dist: cryptography
Requires-Dist: pyjwt
Requires-Dist: requests
Requires-Dist: requests-oauthlib
Provides-Extra: dev
Requires-Dist: bandit ; extra == 'dev'
Requires-Dist: black ; extra == 'dev'
Requires-Dist: doc8 ; extra == 'dev'
Requires-Dist: flake8 ; extra == 'dev'
Requires-Dist: flake8-bugbear ; extra == 'dev'
Requires-Dist: flake8-builtins ; extra == 'dev'
Requires-Dist: flake8-commas ; extra == 'dev'
Requires-Dist: flake8-comprehensions ; extra == 'dev'
Requires-Dist: isort ; extra == 'dev'
Requires-Dist: sphinx ; extra == 'dev'
Requires-Dist: coverage ; extra == 'dev'
Requires-Dist: coveralls ; extra == 'dev'
Requires-Dist: pytest ; extra == 'dev'
Requires-Dist: pytest-cov ; extra == 'dev'
Requires-Dist: pytest-django ; extra == 'dev'
Requires-Dist: tox ; extra == 'dev'
Requires-Dist: versioneer ; extra == 'dev'
Requires-Dist: djangoql ; extra == 'dev'
Requires-Dist: pip-tools ; extra == 'dev'
Requires-Dist: sphinx-rtd-theme ; extra == 'dev'
Requires-Dist: twine ; extra == 'dev'
Provides-Extra: ql
Requires-Dist: djangoql ; extra == 'ql'
Provides-Extra: test
Requires-Dist: coverage ; extra == 'test'
Requires-Dist: coveralls ; extra == 'test'
Requires-Dist: flake8 ; extra == 'test'
Requires-Dist: pytest ; extra == 'test'
Requires-Dist: pytest-cov ; extra == 'test'
Requires-Dist: pytest-django ; extra == 'test'
Requires-Dist: tox ; extra == 'test'
Requires-Dist: versioneer ; extra == 'test'
